OPLS_MD/OPLS.py
OPLS_MD/OPLS_MD.py
OPLS_MD/OPLS_PLS.py
OPLS_MD/PLS.py
OPLS_MD/__init__.py
OPLS_MD/base_PLS.py
OPLS_MD/utils.py
opls_md-0.1.0.dist-info/licenses/LICENSE
opls_md-0.1.0.dist-info/METADATA
opls_md-0.1.0.dist-info/WHEEL
opls_md-0.1.0.dist-info/top_level.txt
opls_md-0.1.0.dist-info/RECORD
