Metadata-Version: 2.4
Name: OPLS-MD
Version: 0.1.0
Summary: PLS and OPLS regressors
Home-page: https://github.com/molecularmachinist/OPLS-MD
Author: "Santeri Paajanen, Shreyas Kaptan"
Author-email: santeri.e.paajanen@helsinki.fi
License: MIT
Project-URL: Bug Tracker, https://github.com/molecularmachinist/OPLS-MD/issues
Classifier: Programming Language :: Python :: 3
Classifier: Operating System :: OS Independent
Classifier: License :: OSI Approved :: MIT License
Requires-Python: >=3.10
License-File: LICENSE
Dynamic: license-file
